af_analysis/__init__.py
af_analysis/analysis.py
af_analysis/clustering.py
af_analysis/data.py
af_analysis/docking.py
af_analysis/plot.py
af_analysis/sequence.py
af_analysis/format/__init__.py
af_analysis/format/af3_local.py
af_analysis/format/af3_webserver.py
af_analysis/format/afpulldown.py
af_analysis/format/boltz1.py
af_analysis/format/chai1.py
af_analysis/format/colabfold_1_5.py
af_analysis/format/default.py
af_analysis/format/massivefold.py
af_analysis/test/__init__.py
af_analysis/test/data_files.py
af_analysis/test/test_analysis.py
af_analysis/test/test_clustering.py
af_analysis/test/test_data.py
af_analysis/test/test_docking.py
af_analysis/test/test_format.py
af_analysis/test/test_sequence.py
af_analysis-0.1.5.dist-info/licenses/LICENSE
af_analysis-0.1.5.dist-info/METADATA
af_analysis-0.1.5.dist-info/WHEEL
af_analysis-0.1.5.dist-info/entry_points.txt
af_analysis-0.1.5.dist-info/top_level.txt
af_analysis-0.1.5.dist-info/RECORD
