Metadata-Version: 2.4
Name: af-analysis
Version: 0.1.5
Summary: `AF analysis` is a python library allowing analysis of Alphafold results.
Author-email: Samuel Murail <samuel.murail@u-paris.fr>
License:  GPL-2.0
Project-URL: Homepage, https://github.com/samuelmurail/af_analysis
Keywords: AlphaFold2,ColabFold,Python,af_analysis
Classifier: Development Status :: 4 - Beta
Classifier: Environment :: Console
Classifier: Intended Audience :: Developers
Classifier: License :: OSI Approved :: BSD License
Classifier: Natural Language :: English
Classifier: Programming Language :: Python
Classifier: Programming Language :: Python :: 3
Classifier: Programming Language :: Python :: 3 :: Only
Classifier: Programming Language :: Python :: 3.9
Classifier: Programming Language :: Python :: Implementation :: CPython
Classifier: Programming Language :: Python :: Implementation :: PyPy
Classifier: Programming Language :: Python :: 3.10
Classifier: Topic :: Software Development
Requires-Python: >=3.8
License-File: LICENSE
Requires-Dist: pdb_numpy>=0.0.12
Requires-Dist: pandas>=1.3.4
Requires-Dist: numpy>=1.21
Requires-Dist: tqdm>=4.0
Requires-Dist: seaborn>=0.11
Requires-Dist: cmcrameri>=1.7
Requires-Dist: nglview>=3.0
Requires-Dist: ipywidgets>=7.6
Requires-Dist: mdanalysis>=2.4
Requires-Dist: scikit-learn
Dynamic: license-file
